custom_components/epb/__init__.py
custom_components/epb/api.py
custom_components/epb/config_flow.py
custom_components/epb/const.py
custom_components/epb/coordinator.py
custom_components/epb/manifest.json
custom_components/epb/sensor.py
custom_components/epb/translations/en.json
ha_epb-1.0.4.dist-info/LICENSE
ha_epb-1.0.4.dist-info/METADATA
ha_epb-1.0.4.dist-info/WHEEL
ha_epb-1.0.4.dist-info/top_level.txt
ha_epb-1.0.4.dist-info/RECORD
