Metadata-Version: 2.2
Name: ha-epb
Version: 1.0.4
Summary: Home Assistant integration for EPB (Electric Power Board)
Home-page: https://github.com/asachs01/ha-epb
Author: Aaron Sachs
Author-email: asachs01@users.noreply.github.com
Keywords: home-assistant,homeassistant,epb,energy,utility
Classifier: Development Status :: 4 - Beta
Classifier: Intended Audience :: Developers
Classifier: License :: OSI Approved :: MIT License
Classifier: Programming Language :: Python :: 3
Classifier: Programming Language :: Python :: 3.9
Classifier: Programming Language :: Python :: 3.10
Classifier: Programming Language :: Python :: 3.11
Classifier: Programming Language :: Python :: 3.12
Requires-Python: >=3.9
License-File: LICENSE
Requires-Dist: aiohttp>=3.8.0
Requires-Dist: attrs>=21.0.0
Requires-Dist: multidict>=4.0.0
Requires-Dist: yarl>=1.0.0
Requires-Dist: frozenlist>=1.0.0
Requires-Dist: typing-extensions>=4.0.0
Dynamic: author
Dynamic: author-email
Dynamic: classifier
Dynamic: description
Dynamic: description-content-type
Dynamic: home-page
Dynamic: keywords
Dynamic: requires-dist
Dynamic: requires-python
Dynamic: summary
